{
  "type": "Program",
  "body": [
    {
      "type": "ExpressionStatement",
      "expression": {
        "type": "CallExpression",
        "callee": {
          "type": "FunctionExpression",
          "id": null,
          "params": [],
          "body": {
            "type": "BlockStatement",
            "body": [
              {
                "type": "VariableDeclaration",
                "declarations": [
                  {
                    "type": "VariableDeclarator",
                    "id": {
                      "type": "Identifier",
                      "name": "matched",
                      "range": [
                        122,
                        129
                      ],
                      "loc": {
                        "start": {
                          "line": 4,
                          "column": 6
                        },
                        "end": {
                          "line": 4,
                          "column": 13
                        }
                      }
                    },
                    "init": {
                      "type": "CallExpression",
                      "callee": {
                        "type": "MemberExpression",
                        "computed": false,
                        "object": {
                          "type": "MemberExpression",
                          "computed": false,
                          "object": {
                            "type": "Identifier",
                            "name": "location",
                            "range": [
                              132,
                              140
                            ],
                            "loc": {
                              "start": {
                                "line": 4,
                                "column": 16
                              },
                              "end": {
                                "line": 4,
                                "column": 24
                              }
                            }
                          },
                          "property": {
                            "type": "Identifier",
                            "name": "hash",
                            "range": [
                              141,
                              145
                            ],
                            "loc": {
                              "start": {
                                "line": 4,
                                "column": 25
                              },
                              "end": {
                                "line": 4,
                                "column": 29
                              }
                            }
                          },
                          "range": [
                            132,
                            145
                          ],
                          "loc": {
                            "start": {
                              "line": 4,
                              "column": 16
                            },
                            "end": {
                              "line": 4,
                              "column": 29
                            }
                          }
                        },
                        "property": {
                          "type": "Identifier",
                          "name": "match",
                          "range": [
                            146,
                            151
                          ],
                          "loc": {
                            "start": {
                              "line": 4,
                              "column": 30
                            },
                            "end": {
                              "line": 4,
                              "column": 35
                            }
                          }
                        },
                        "range": [
                          132,
                          151
                        ],
                        "loc": {
                          "start": {
                            "line": 4,
                            "column": 16
                          },
                          "end": {
                            "line": 4,
                            "column": 35
                          }
                        }
                      },
                      "arguments": [
                        {
                          "type": "Literal",
                          "value": {},
                          "raw": "/errorLines=([\\d,]+)/",
                          "regex": {
                            "pattern": "errorLines=([\\d,]+)",
                            "flags": ""
                          },
                          "range": [
                            152,
                            173
                          ],
                          "loc": {
                            "start": {
                              "line": 4,
                              "column": 36
                            },
                            "end": {
                              "line": 4,
                              "column": 57
                            }
                          }
                        }
                      ],
                      "range": [
                        132,
                        174
                      ],
                      "loc": {
                        "start": {
                          "line": 4,
                          "column": 16
                        },
                        "end": {
                          "line": 4,
                          "column": 58
                        }
                      }
                    },
                    "range": [
                      122,
                      174
                    ],
                    "loc": {
                      "start": {
                        "line": 4,
                        "column": 6
                      },
                      "end": {
                        "line": 4,
                        "column": 58
                      }
                    }
                  }
                ],
                "kind": "var",
                "range": [
                  118,
                  175
                ],
                "loc": {
                  "start": {
                    "line": 4,
                    "column": 2
                  },
                  "end": {
                    "line": 4,
                    "column": 59
                  }
                }
              },
              {
                "type": "IfStatement",
                "test": {
                  "type": "Identifier",
                  "name": "matched",
                  "range": [
                    182,
                    189
                  ],
                  "loc": {
                    "start": {
                      "line": 5,
                      "column": 6
                    },
                    "end": {
                      "line": 5,
                      "column": 13
                    }
                  }
                },
                "consequent": {
                  "type": "ReturnStatement",
                  "argument": null,
                  "range": [
                    191,
                    198
                  ],
                  "loc": {
                    "start": {
                      "line": 5,
                      "column": 15
                    },
                    "end": {
                      "line": 5,
                      "column": 22
                    }
                  }
                },
                "alternate": null,
                "range": [
                  178,
                  198
                ],
                "loc": {
                  "start": {
                    "line": 5,
                    "column": 2
                  },
                  "end": {
                    "line": 5,
                    "column": 22
                  }
                }
              },
              {
                "type": "FunctionDeclaration",
                "id": {
                  "type": "Identifier",
                  "name": "adjust",
                  "range": [
                    211,
                    217
                  ],
                  "loc": {
                    "start": {
                      "line": 7,
                      "column": 11
                    },
                    "end": {
                      "line": 7,
                      "column": 17
                    }
                  }
                },
                "params": [],
                "body": {
                  "type": "BlockStatement",
                  "body": [
                    {
                      "type": "ExpressionStatement",
                      "expression": {
                        "type": "CallExpression",
                        "callee": {
                          "type": "MemberExpression",
                          "computed": false,
                          "object": {
                            "type": "Identifier",
                            "name": "window",
                            "range": [
                              226,
                              232
                            ],
                            "loc": {
                              "start": {
                                "line": 8,
                                "column": 4
                              },
                              "end": {
                                "line": 8,
                                "column": 10
                              }
                            }
                          },
                          "property": {
                            "type": "Identifier",
                            "name": "scrollBy",
                            "range": [
                              233,
                              241
                            ],
                            "loc": {
                              "start": {
                                "line": 8,
                                "column": 11
                              },
                              "end": {
                                "line": 8,
                                "column": 19
                              }
                            }
                          },
                          "range": [
                            226,
                            241
                          ],
                          "loc": {
                            "start": {
                              "line": 8,
                              "column": 4
                            },
                            "end": {
                              "line": 8,
                              "column": 19
                            }
                          }
                        },
                        "arguments": [
                          {
                            "type": "Literal",
                            "value": 0,
                            "raw": "0",
                            "range": [
                              242,
                              243
                            ],
                            "loc": {
                              "start": {
                                "line": 8,
                                "column": 20
                              },
                              "end": {
                                "line": 8,
                                "column": 21
                              }
                            }
                          },
                          {
                            "type": "UnaryExpression",
                            "operator": "-",
                            "argument": {
                              "type": "Literal",
                              "value": 55,
                              "raw": "55",
                              "range": [
                                246,
                                248
                              ],
                              "loc": {
                                "start": {
                                  "line": 8,
                                  "column": 24
                                },
                                "end": {
                                  "line": 8,
                                  "column": 26
                                }
                              }
                            },
                            "prefix": true,
                            "range": [
                              245,
                              248
                            ],
                            "loc": {
                              "start": {
                                "line": 8,
                                "column": 23
                              },
                              "end": {
                                "line": 8,
                                "column": 26
                              }
                            }
                          }
                        ],
                        "range": [
                          226,
                          249
                        ],
                        "loc": {
                          "start": {
                            "line": 8,
                            "column": 4
                          },
                          "end": {
                            "line": 8,
                            "column": 27
                          }
                        }
                      },
                      "range": [
                        226,
                        250
                      ],
                      "loc": {
                        "start": {
                          "line": 8,
                          "column": 4
                        },
                        "end": {
                          "line": 8,
                          "column": 28
                        }
                      }
                    },
                    {
                      "type": "VariableDeclaration",
                      "declarations": [
                        {
                          "type": "VariableDeclarator",
                          "id": {
                            "type": "Identifier",
                            "name": "el",
                            "range": [
                              259,
                              261
                            ],
                            "loc": {
                              "start": {
                                "line": 9,
                                "column": 8
                              },
                              "end": {
                                "line": 9,
                                "column": 10
                              }
                            }
                          },
                          "init": {
                            "type": "CallExpression",
                            "callee": {
                              "type": "MemberExpression",
                              "computed": false,
                              "object": {
                                "type": "Identifier",
                                "name": "document",
                                "range": [
                                  264,
                                  272
                                ],
                                "loc": {
                                  "start": {
                                    "line": 9,
                                    "column": 13
                                  },
                                  "end": {
                                    "line": 9,
                                    "column": 21
                                  }
                                }
                              },
                              "property": {
                                "type": "Identifier",
                                "name": "querySelector",
                                "range": [
                                  273,
                                  286
                                ],
                                "loc": {
                                  "start": {
                                    "line": 9,
                                    "column": 22
                                  },
                                  "end": {
                                    "line": 9,
                                    "column": 35
                                  }
                                }
                              },
                              "range": [
                                264,
                                286
                              ],
                              "loc": {
                                "start": {
                                  "line": 9,
                                  "column": 13
                                },
                                "end": {
                                  "line": 9,
                                  "column": 35
                                }
                              }
                            },
                            "arguments": [
                              {
                                "type": "Literal",
                                "value": ".inner-link-active",
                                "raw": "'.inner-link-active'",
                                "range": [
                                  287,
                                  307
                                ],
                                "loc": {
                                  "start": {
                                    "line": 9,
                                    "column": 36
                                  },
                                  "end": {
                                    "line": 9,
                                    "column": 56
                                  }
                                }
                              }
                            ],
                            "range": [
                              264,
                              308
                            ],
                            "loc": {
                              "start": {
                                "line": 9,
                                "column": 13
                              },
                              "end": {
                                "line": 9,
                                "column": 57
                              }
                            }
                          },
                          "range": [
                            259,
                            308
                          ],
                          "loc": {
                            "start": {
                              "line": 9,
                              "column": 8
                            },
                            "end": {
                              "line": 9,
                              "column": 57
                            }
                          }
                        }
                      ],
                      "kind": "var",
                      "range": [
                        255,
                        309
                      ],
                      "loc": {
                        "start": {
                          "line": 9,
                          "column": 4
                        },
                        "end": {
                          "line": 9,
                          "column": 58
                        }
                      }
                    },
                    {
                      "type": "IfStatement",
                      "test": {
                        "type": "Identifier",
                        "name": "el",
                        "range": [
                          318,
                          320
                        ],
                        "loc": {
                          "start": {
                            "line": 10,
                            "column": 8
                          },
                          "end": {
                            "line": 10,
                            "column": 10
                          }
                        }
                      },
                      "consequent": {
                        "type": "ExpressionStatement",
                        "expression": {
                          "type": "CallExpression",
                          "callee": {
                            "type": "MemberExpression",
                            "computed": false,
                            "object": {
                              "type": "MemberExpression",
                              "computed": false,
                              "object": {
                                "type": "Identifier",
                                "name": "el",
                                "range": [
                                  322,
                                  324
                                ],
                                "loc": {
                                  "start": {
                                    "line": 10,
                                    "column": 12
                                  },
                                  "end": {
                                    "line": 10,
                                    "column": 14
                                  }
                                }
                              },
                              "property": {
                                "type": "Identifier",
                                "name": "classList",
                                "range": [
                                  325,
                                  334
                                ],
                                "loc": {
                                  "start": {
                                    "line": 10,
                                    "column": 15
                                  },
                                  "end": {
                                    "line": 10,
                                    "column": 24
                                  }
                                }
                              },
                              "range": [
                                322,
                                334
                              ],
                              "loc": {
                                "start": {
                                  "line": 10,
                                  "column": 12
                                },
                                "end": {
                                  "line": 10,
                                  "column": 24
                                }
                              }
                            },
                            "property": {
                              "type": "Identifier",
                              "name": "remove",
                              "range": [
                                335,
                                341
                              ],
                              "loc": {
                                "start": {
                                  "line": 10,
                                  "column": 25
                                },
                                "end": {
                                  "line": 10,
                                  "column": 31
                                }
                              }
                            },
                            "range": [
                              322,
                              341
                            ],
                            "loc": {
                              "start": {
                                "line": 10,
                                "column": 12
                              },
                              "end": {
                                "line": 10,
                                "column": 31
                              }
                            }
                          },
                          "arguments": [
                            {
                              "type": "Literal",
                              "value": "inner-link-active",
                              "raw": "'inner-link-active'",
                              "range": [
                                342,
                                361
                              ],
                              "loc": {
                                "start": {
                                  "line": 10,
                                  "column": 32
                                },
                                "end": {
                                  "line": 10,
                                  "column": 51
                                }
                              }
                            }
                          ],
                          "range": [
                            322,
                            362
                          ],
                          "loc": {
                            "start": {
                              "line": 10,
                              "column": 12
                            },
                            "end": {
                              "line": 10,
                              "column": 52
                            }
                          }
                        },
                        "range": [
                          322,
                          363
                        ],
                        "loc": {
                          "start": {
                            "line": 10,
                            "column": 12
                          },
                          "end": {
                            "line": 10,
                            "column": 53
                          }
                        }
                      },
                      "alternate": null,
                      "range": [
                        314,
                        363
                      ],
                      "loc": {
                        "start": {
                          "line": 10,
                          "column": 4
                        },
                        "end": {
                          "line": 10,
                          "column": 53
                        }
                      },
                      "trailingComments": [
                        {
                          "type": "Line",
                          "value": " ``[ ] . ' \" @`` are not valid in DOM id. so must escape these.",
                          "range": [
                            369,
                            434
                          ],
                          "loc": {
                            "start": {
                              "line": 12,
                              "column": 4
                            },
                            "end": {
                              "line": 12,
                              "column": 69
                            }
                          }
                        }
                      ]
                    },
                    {
                      "type": "VariableDeclaration",
                      "declarations": [
                        {
                          "type": "VariableDeclarator",
                          "id": {
                            "type": "Identifier",
                            "name": "id",
                            "range": [
                              443,
                              445
                            ],
                            "loc": {
                              "start": {
                                "line": 13,
                                "column": 8
                              },
                              "end": {
                                "line": 13,
                                "column": 10
                              }
                            }
                          },
                          "init": {
                            "type": "CallExpression",
                            "callee": {
                              "type": "MemberExpression",
                              "computed": false,
                              "object": {
                                "type": "MemberExpression",
                                "computed": false,
                                "object": {
                                  "type": "Identifier",
                                  "name": "location",
                                  "range": [
                                    448,
                                    456
                                  ],
                                  "loc": {
                                    "start": {
                                      "line": 13,
                                      "column": 13
                                    },
                                    "end": {
                                      "line": 13,
                                      "column": 21
                                    }
                                  }
                                },
                                "property": {
                                  "type": "Identifier",
                                  "name": "hash",
                                  "range": [
                                    457,
                                    461
                                  ],
                                  "loc": {
                                    "start": {
                                      "line": 13,
                                      "column": 22
                                    },
                                    "end": {
                                      "line": 13,
                                      "column": 26
                                    }
                                  }
                                },
                                "range": [
                                  448,
                                  461
                                ],
                                "loc": {
                                  "start": {
                                    "line": 13,
                                    "column": 13
                                  },
                                  "end": {
                                    "line": 13,
                                    "column": 26
                                  }
                                }
                              },
                              "property": {
                                "type": "Identifier",
                                "name": "replace",
                                "range": [
                                  462,
                                  469
                                ],
                                "loc": {
                                  "start": {
                                    "line": 13,
                                    "column": 27
                                  },
                                  "end": {
                                    "line": 13,
                                    "column": 34
                                  }
                                }
                              },
                              "range": [
                                448,
                                469
                              ],
                              "loc": {
                                "start": {
                                  "line": 13,
                                  "column": 13
                                },
                                "end": {
                                  "line": 13,
                                  "column": 34
                                }
                              }
                            },
                            "arguments": [
                              {
                                "type": "Literal",
                                "value": {},
                                "raw": "/([\\[\\].'\"@$])/g",
                                "regex": {
                                  "pattern": "([\\[\\].'\"@$])",
                                  "flags": "g"
                                },
                                "range": [
                                  470,
                                  486
                                ],
                                "loc": {
                                  "start": {
                                    "line": 13,
                                    "column": 35
                                  },
                                  "end": {
                                    "line": 13,
                                    "column": 51
                                  }
                                }
                              },
                              {
                                "type": "Literal",
                                "value": "\\$1",
                                "raw": "'\\\\$1'",
                                "range": [
                                  488,
                                  494
                                ],
                                "loc": {
                                  "start": {
                                    "line": 13,
                                    "column": 53
                                  },
                                  "end": {
                                    "line": 13,
                                    "column": 59
                                  }
                                }
                              }
                            ],
                            "range": [
                              448,
                              495
                            ],
                            "loc": {
                              "start": {
                                "line": 13,
                                "column": 13
                              },
                              "end": {
                                "line": 13,
                                "column": 60
                              }
                            }
                          },
                          "range": [
                            443,
                            495
                          ],
                          "loc": {
                            "start": {
                              "line": 13,
                              "column": 8
                            },
                            "end": {
                              "line": 13,
                              "column": 60
                            }
                          }
                        }
                      ],
                      "kind": "var",
                      "range": [
                        439,
                        496
                      ],
                      "loc": {
                        "start": {
                          "line": 13,
                          "column": 4
                        },
                        "end": {
                          "line": 13,
                          "column": 61
                        }
                      },
                      "leadingComments": [
                        {
                          "type": "Line",
                          "value": " ``[ ] . ' \" @`` are not valid in DOM id. so must escape these.",
                          "range": [
                            369,
                            434
                          ],
                          "loc": {
                            "start": {
                              "line": 12,
                              "column": 4
                            },
                            "end": {
                              "line": 12,
                              "column": 69
                            }
                          }
                        }
                      ]
                    },
                    {
                      "type": "VariableDeclaration",
                      "declarations": [
                        {
                          "type": "VariableDeclarator",
                          "id": {
                            "type": "Identifier",
                            "name": "el",
                            "range": [
                              505,
                              507
                            ],
                            "loc": {
                              "start": {
                                "line": 14,
                                "column": 8
                              },
                              "end": {
                                "line": 14,
                                "column": 10
                              }
                            }
                          },
                          "init": {
                            "type": "CallExpression",
                            "callee": {
                              "type": "MemberExpression",
                              "computed": false,
                              "object": {
                                "type": "Identifier",
                                "name": "document",
                                "range": [
                                  510,
                                  518
                                ],
                                "loc": {
                                  "start": {
                                    "line": 14,
                                    "column": 13
                                  },
                                  "end": {
                                    "line": 14,
                                    "column": 21
                                  }
                                }
                              },
                              "property": {
                                "type": "Identifier",
                                "name": "querySelector",
                                "range": [
                                  519,
                                  532
                                ],
                                "loc": {
                                  "start": {
                                    "line": 14,
                                    "column": 22
                                  },
                                  "end": {
                                    "line": 14,
                                    "column": 35
                                  }
                                }
                              },
                              "range": [
                                510,
                                532
                              ],
                              "loc": {
                                "start": {
                                  "line": 14,
                                  "column": 13
                                },
                                "end": {
                                  "line": 14,
                                  "column": 35
                                }
                              }
                            },
                            "arguments": [
                              {
                                "type": "Identifier",
                                "name": "id",
                                "range": [
                                  533,
                                  535
                                ],
                                "loc": {
                                  "start": {
                                    "line": 14,
                                    "column": 36
                                  },
                                  "end": {
                                    "line": 14,
                                    "column": 38
                                  }
                                }
                              }
                            ],
                            "range": [
                              510,
                              536
                            ],
                            "loc": {
                              "start": {
                                "line": 14,
                                "column": 13
                              },
                              "end": {
                                "line": 14,
                                "column": 39
                              }
                            }
                          },
                          "range": [
                            505,
                            536
                          ],
                          "loc": {
                            "start": {
                              "line": 14,
                              "column": 8
                            },
                            "end": {
                              "line": 14,
                              "column": 39
                            }
                          }
                        }
                      ],
                      "kind": "var",
                      "range": [
                        501,
                        537
                      ],
                      "loc": {
                        "start": {
                          "line": 14,
                          "column": 4
                        },
                        "end": {
                          "line": 14,
                          "column": 40
                        }
                      }
                    },
                    {
                      "type": "IfStatement",
                      "test": {
                        "type": "Identifier",
                        "name": "el",
                        "range": [
                          546,
                          548
                        ],
                        "loc": {
                          "start": {
                            "line": 15,
                            "column": 8
                          },
                          "end": {
                            "line": 15,
                            "column": 10
                          }
                        }
                      },
                      "consequent": {
                        "type": "ExpressionStatement",
                        "expression": {
                          "type": "CallExpression",
                          "callee": {
                            "type": "MemberExpression",
                            "computed": false,
                            "object": {
                              "type": "MemberExpression",
                              "computed": false,
                              "object": {
                                "type": "Identifier",
                                "name": "el",
                                "range": [
                                  550,
                                  552
                                ],
                                "loc": {
                                  "start": {
                                    "line": 15,
                                    "column": 12
                                  },
                                  "end": {
                                    "line": 15,
                                    "column": 14
                                  }
                                }
                              },
                              "property": {
                                "type": "Identifier",
                                "name": "classList",
                                "range": [
                                  553,
                                  562
                                ],
                                "loc": {
                                  "start": {
                                    "line": 15,
                                    "column": 15
                                  },
                                  "end": {
                                    "line": 15,
                                    "column": 24
                                  }
                                }
                              },
                              "range": [
                                550,
                                562
                              ],
                              "loc": {
                                "start": {
                                  "line": 15,
                                  "column": 12
                                },
                                "end": {
                                  "line": 15,
                                  "column": 24
                                }
                              }
                            },
                            "property": {
                              "type": "Identifier",
                              "name": "add",
                              "range": [
                                563,
                                566
                              ],
                              "loc": {
                                "start": {
                                  "line": 15,
                                  "column": 25
                                },
                                "end": {
                                  "line": 15,
                                  "column": 28
                                }
                              }
                            },
                            "range": [
                              550,
                              566
                            ],
                            "loc": {
                              "start": {
                                "line": 15,
                                "column": 12
                              },
                              "end": {
                                "line": 15,
                                "column": 28
                              }
                            }
                          },
                          "arguments": [
                            {
                              "type": "Literal",
                              "value": "inner-link-active",
                              "raw": "'inner-link-active'",
                              "range": [
                                567,
                                586
                              ],
                              "loc": {
                                "start": {
                                  "line": 15,
                                  "column": 29
                                },
                                "end": {
                                  "line": 15,
                                  "column": 48
                                }
                              }
                            }
                          ],
                          "range": [
                            550,
                            587
                          ],
                          "loc": {
                            "start": {
                              "line": 15,
                              "column": 12
                            },
                            "end": {
                              "line": 15,
                              "column": 49
                            }
                          }
                        },
                        "range": [
                          550,
                          588
                        ],
                        "loc": {
                          "start": {
                            "line": 15,
                            "column": 12
                          },
                          "end": {
                            "line": 15,
                            "column": 50
                          }
                        }
                      },
                      "alternate": null,
                      "range": [
                        542,
                        588
                      ],
                      "loc": {
                        "start": {
                          "line": 15,
                          "column": 4
                        },
                        "end": {
                          "line": 15,
                          "column": 50
                        }
                      }
                    }
                  ],
                  "range": [
                    220,
                    592
                  ],
                  "loc": {
                    "start": {
                      "line": 7,
                      "column": 20
                    },
                    "end": {
                      "line": 16,
                      "column": 3
                    }
                  }
                },
                "generator": false,
                "expression": false,
                "range": [
                  202,
                  592
                ],
                "loc": {
                  "start": {
                    "line": 7,
                    "column": 2
                  },
                  "end": {
                    "line": 16,
                    "column": 3
                  }
                }
              },
              {
                "type": "ExpressionStatement",
                "expression": {
                  "type": "CallExpression",
                  "callee": {
                    "type": "MemberExpression",
                    "computed": false,
                    "object": {
                      "type": "Identifier",
                      "name": "window",
                      "range": [
                        596,
                        602
                      ],
                      "loc": {
                        "start": {
                          "line": 18,
                          "column": 2
                        },
                        "end": {
                          "line": 18,
                          "column": 8
                        }
                      }
                    },
                    "property": {
                      "type": "Identifier",
                      "name": "addEventListener",
                      "range": [
                        603,
                        619
                      ],
                      "loc": {
                        "start": {
                          "line": 18,
                          "column": 9
                        },
                        "end": {
                          "line": 18,
                          "column": 25
                        }
                      }
                    },
                    "range": [
                      596,
                      619
                    ],
                    "loc": {
                      "start": {
                        "line": 18,
                        "column": 2
                      },
                      "end": {
                        "line": 18,
                        "column": 25
                      }
                    }
                  },
                  "arguments": [
                    {
                      "type": "Literal",
                      "value": "hashchange",
                      "raw": "'hashchange'",
                      "range": [
                        620,
                        632
                      ],
                      "loc": {
                        "start": {
                          "line": 18,
                          "column": 26
                        },
                        "end": {
                          "line": 18,
                          "column": 38
                        }
                      }
                    },
                    {
                      "type": "Identifier",
                      "name": "adjust",
                      "range": [
                        634,
                        640
                      ],
                      "loc": {
                        "start": {
                          "line": 18,
                          "column": 40
                        },
                        "end": {
                          "line": 18,
                          "column": 46
                        }
                      }
                    }
                  ],
                  "range": [
                    596,
                    641
                  ],
                  "loc": {
                    "start": {
                      "line": 18,
                      "column": 2
                    },
                    "end": {
                      "line": 18,
                      "column": 47
                    }
                  }
                },
                "range": [
                  596,
                  642
                ],
                "loc": {
                  "start": {
                    "line": 18,
                    "column": 2
                  },
                  "end": {
                    "line": 18,
                    "column": 48
                  }
                }
              },
              {
                "type": "IfStatement",
                "test": {
                  "type": "MemberExpression",
                  "computed": false,
                  "object": {
                    "type": "Identifier",
                    "name": "location",
                    "range": [
                      650,
                      658
                    ],
                    "loc": {
                      "start": {
                        "line": 20,
                        "column": 6
                      },
                      "end": {
                        "line": 20,
                        "column": 14
                      }
                    }
                  },
                  "property": {
                    "type": "Identifier",
                    "name": "hash",
                    "range": [
                      659,
                      663
                    ],
                    "loc": {
                      "start": {
                        "line": 20,
                        "column": 15
                      },
                      "end": {
                        "line": 20,
                        "column": 19
                      }
                    }
                  },
                  "range": [
                    650,
                    663
                  ],
                  "loc": {
                    "start": {
                      "line": 20,
                      "column": 6
                    },
                    "end": {
                      "line": 20,
                      "column": 19
                    }
                  }
                },
                "consequent": {
                  "type": "BlockStatement",
                  "body": [
                    {
                      "type": "ExpressionStatement",
                      "expression": {
                        "type": "CallExpression",
                        "callee": {
                          "type": "Identifier",
                          "name": "setTimeout",
                          "range": [
                            671,
                            681
                          ],
                          "loc": {
                            "start": {
                              "line": 21,
                              "column": 4
                            },
                            "end": {
                              "line": 21,
                              "column": 14
                            }
                          }
                        },
                        "arguments": [
                          {
                            "type": "Identifier",
                            "name": "adjust",
                            "range": [
                              682,
                              688
                            ],
                            "loc": {
                              "start": {
                                "line": 21,
                                "column": 15
                              },
                              "end": {
                                "line": 21,
                                "column": 21
                              }
                            }
                          },
                          {
                            "type": "Literal",
                            "value": 0,
                            "raw": "0",
                            "range": [
                              690,
                              691
                            ],
                            "loc": {
                              "start": {
                                "line": 21,
                                "column": 23
                              },
                              "end": {
                                "line": 21,
                                "column": 24
                              }
                            }
                          }
                        ],
                        "range": [
                          671,
                          692
                        ],
                        "loc": {
                          "start": {
                            "line": 21,
                            "column": 4
                          },
                          "end": {
                            "line": 21,
                            "column": 25
                          }
                        }
                      },
                      "range": [
                        671,
                        693
                      ],
                      "loc": {
                        "start": {
                          "line": 21,
                          "column": 4
                        },
                        "end": {
                          "line": 21,
                          "column": 26
                        }
                      }
                    }
                  ],
                  "range": [
                    665,
                    697
                  ],
                  "loc": {
                    "start": {
                      "line": 20,
                      "column": 21
                    },
                    "end": {
                      "line": 22,
                      "column": 3
                    }
                  }
                },
                "alternate": null,
                "range": [
                  646,
                  697
                ],
                "loc": {
                  "start": {
                    "line": 20,
                    "column": 2
                  },
                  "end": {
                    "line": 22,
                    "column": 3
                  }
                }
              }
            ],
            "range": [
              114,
              699
            ],
            "loc": {
              "start": {
                "line": 3,
                "column": 11
              },
              "end": {
                "line": 23,
                "column": 1
              }
            }
          },
          "generator": false,
          "expression": false,
          "range": [
            104,
            699
          ],
          "loc": {
            "start": {
              "line": 3,
              "column": 1
            },
            "end": {
              "line": 23,
              "column": 1
            }
          }
        },
        "arguments": [],
        "range": [
          103,
          702
        ],
        "loc": {
          "start": {
            "line": 3,
            "column": 0
          },
          "end": {
            "line": 23,
            "column": 4
          }
        }
      },
      "range": [
        103,
        703
      ],
      "loc": {
        "start": {
          "line": 3,
          "column": 0
        },
        "end": {
          "line": 23,
          "column": 5
        }
      },
      "leadingComments": [
        {
          "type": "Line",
          "value": " inner link(#foo) can not correctly scroll, because page has fixed header,",
          "range": [
            0,
            76
          ],
          "loc": {
            "start": {
              "line": 1,
              "column": 0
            },
            "end": {
              "line": 1,
              "column": 76
            }
          }
        },
        {
          "type": "Line",
          "value": " so, I manually scroll.",
          "range": [
            77,
            102
          ],
          "loc": {
            "start": {
              "line": 2,
              "column": 0
            },
            "end": {
              "line": 2,
              "column": 25
            }
          }
        }
      ]
    },
    {
      "type": "ExpressionStatement",
      "expression": {
        "type": "CallExpression",
        "callee": {
          "type": "FunctionExpression",
          "id": null,
          "params": [],
          "body": {
            "type": "BlockStatement",
            "body": [
              {
                "type": "VariableDeclaration",
                "declarations": [
                  {
                    "type": "VariableDeclarator",
                    "id": {
                      "type": "Identifier",
                      "name": "els",
                      "range": [
                        724,
                        727
                      ],
                      "loc": {
                        "start": {
                          "line": 26,
                          "column": 6
                        },
                        "end": {
                          "line": 26,
                          "column": 9
                        }
                      }
                    },
                    "init": {
                      "type": "CallExpression",
                      "callee": {
                        "type": "MemberExpression",
                        "computed": false,
                        "object": {
                          "type": "Identifier",
                          "name": "document",
                          "range": [
                            730,
                            738
                          ],
                          "loc": {
                            "start": {
                              "line": 26,
                              "column": 12
                            },
                            "end": {
                              "line": 26,
                              "column": 20
                            }
                          }
                        },
                        "property": {
                          "type": "Identifier",
                          "name": "querySelectorAll",
                          "range": [
                            739,
                            755
                          ],
                          "loc": {
                            "start": {
                              "line": 26,
                              "column": 21
                            },
                            "end": {
                              "line": 26,
                              "column": 37
                            }
                          }
                        },
                        "range": [
                          730,
                          755
                        ],
                        "loc": {
                          "start": {
                            "line": 26,
                            "column": 12
                          },
                          "end": {
                            "line": 26,
                            "column": 37
                          }
                        }
                      },
                      "arguments": [
                        {
                          "type": "Literal",
                          "value": "[href^=\"#\"]",
                          "raw": "'[href^=\"#\"]'",
                          "range": [
                            756,
                            769
                          ],
                          "loc": {
                            "start": {
                              "line": 26,
                              "column": 38
                            },
                            "end": {
                              "line": 26,
                              "column": 51
                            }
                          }
                        }
                      ],
                      "range": [
                        730,
                        770
                      ],
                      "loc": {
                        "start": {
                          "line": 26,
                          "column": 12
                        },
                        "end": {
                          "line": 26,
                          "column": 52
                        }
                      }
                    },
                    "range": [
                      724,
                      770
                    ],
                    "loc": {
                      "start": {
                        "line": 26,
                        "column": 6
                      },
                      "end": {
                        "line": 26,
                        "column": 52
                      }
                    }
                  }
                ],
                "kind": "var",
                "range": [
                  720,
                  771
                ],
                "loc": {
                  "start": {
                    "line": 26,
                    "column": 2
                  },
                  "end": {
                    "line": 26,
                    "column": 53
                  }
                }
              },
              {
                "type": "ForStatement",
                "init": {
                  "type": "VariableDeclaration",
                  "declarations": [
                    {
                      "type": "VariableDeclarator",
                      "id": {
                        "type": "Identifier",
                        "name": "i",
                        "range": [
                          783,
                          784
                        ],
                        "loc": {
                          "start": {
                            "line": 27,
                            "column": 11
                          },
                          "end": {
                            "line": 27,
                            "column": 12
                          }
                        }
                      },
                      "init": {
                        "type": "Literal",
                        "value": 0,
                        "raw": "0",
                        "range": [
                          787,
                          788
                        ],
                        "loc": {
                          "start": {
                            "line": 27,
                            "column": 15
                          },
                          "end": {
                            "line": 27,
                            "column": 16
                          }
                        }
                      },
                      "range": [
                        783,
                        788
                      ],
                      "loc": {
                        "start": {
                          "line": 27,
                          "column": 11
                        },
                        "end": {
                          "line": 27,
                          "column": 16
                        }
                      }
                    }
                  ],
                  "kind": "var",
                  "range": [
                    779,
                    788
                  ],
                  "loc": {
                    "start": {
                      "line": 27,
                      "column": 7
                    },
                    "end": {
                      "line": 27,
                      "column": 16
                    }
                  }
                },
                "test": {
                  "type": "BinaryExpression",
                  "operator": "<",
                  "left": {
                    "type": "Identifier",
                    "name": "i",
                    "range": [
                      790,
                      791
                    ],
                    "loc": {
                      "start": {
                        "line": 27,
                        "column": 18
                      },
                      "end": {
                        "line": 27,
                        "column": 19
                      }
                    }
                  },
                  "right": {
                    "type": "MemberExpression",
                    "computed": false,
                    "object": {
                      "type": "Identifier",
                      "name": "els",
                      "range": [
                        794,
                        797
                      ],
                      "loc": {
                        "start": {
                          "line": 27,
                          "column": 22
                        },
                        "end": {
                          "line": 27,
                          "column": 25
                        }
                      }
                    },
                    "property": {
                      "type": "Identifier",
                      "name": "length",
                      "range": [
                        798,
                        804
                      ],
                      "loc": {
                        "start": {
                          "line": 27,
                          "column": 26
                        },
                        "end": {
                          "line": 27,
                          "column": 32
                        }
                      }
                    },
                    "range": [
                      794,
                      804
                    ],
                    "loc": {
                      "start": {
                        "line": 27,
                        "column": 22
                      },
                      "end": {
                        "line": 27,
                        "column": 32
                      }
                    }
                  },
                  "range": [
                    790,
                    804
                  ],
                  "loc": {
                    "start": {
                      "line": 27,
                      "column": 18
                    },
                    "end": {
                      "line": 27,
                      "column": 32
                    }
                  }
                },
                "update": {
                  "type": "UpdateExpression",
                  "operator": "++",
                  "argument": {
                    "type": "Identifier",
                    "name": "i",
                    "range": [
                      806,
                      807
                    ],
                    "loc": {
                      "start": {
                        "line": 27,
                        "column": 34
                      },
                      "end": {
                        "line": 27,
                        "column": 35
                      }
                    }
                  },
                  "prefix": false,
                  "range": [
                    806,
                    809
                  ],
                  "loc": {
                    "start": {
                      "line": 27,
                      "column": 34
                    },
                    "end": {
                      "line": 27,
                      "column": 37
                    }
                  }
                },
                "body": {
                  "type": "BlockStatement",
                  "body": [
                    {
                      "type": "VariableDeclaration",
                      "declarations": [
                        {
                          "type": "VariableDeclarator",
                          "id": {
                            "type": "Identifier",
                            "name": "el",
                            "range": [
                              821,
                              823
                            ],
                            "loc": {
                              "start": {
                                "line": 28,
                                "column": 8
                              },
                              "end": {
                                "line": 28,
                                "column": 10
                              }
                            }
                          },
                          "init": {
                            "type": "MemberExpression",
                            "computed": true,
                            "object": {
                              "type": "Identifier",
                              "name": "els",
                              "range": [
                                826,
                                829
                              ],
                              "loc": {
                                "start": {
                                  "line": 28,
                                  "column": 13
                                },
                                "end": {
                                  "line": 28,
                                  "column": 16
                                }
                              }
                            },
                            "property": {
                              "type": "Identifier",
                              "name": "i",
                              "range": [
                                830,
                                831
                              ],
                              "loc": {
                                "start": {
                                  "line": 28,
                                  "column": 17
                                },
                                "end": {
                                  "line": 28,
                                  "column": 18
                                }
                              }
                            },
                            "range": [
                              826,
                              832
                            ],
                            "loc": {
                              "start": {
                                "line": 28,
                                "column": 13
                              },
                              "end": {
                                "line": 28,
                                "column": 19
                              }
                            }
                          },
                          "range": [
                            821,
                            832
                          ],
                          "loc": {
                            "start": {
                              "line": 28,
                              "column": 8
                            },
                            "end": {
                              "line": 28,
                              "column": 19
                            }
                          }
                        }
                      ],
                      "kind": "var",
                      "range": [
                        817,
                        833
                      ],
                      "loc": {
                        "start": {
                          "line": 28,
                          "column": 4
                        },
                        "end": {
                          "line": 28,
                          "column": 20
                        }
                      }
                    },
                    {
                      "type": "ExpressionStatement",
                      "expression": {
                        "type": "AssignmentExpression",
                        "operator": "=",
                        "left": {
                          "type": "MemberExpression",
                          "computed": false,
                          "object": {
                            "type": "Identifier",
                            "name": "el",
                            "range": [
                              838,
                              840
                            ],
                            "loc": {
                              "start": {
                                "line": 29,
                                "column": 4
                              },
                              "end": {
                                "line": 29,
                                "column": 6
                              }
                            }
                          },
                          "property": {
                            "type": "Identifier",
                            "name": "href",
                            "range": [
                              841,
                              845
                            ],
                            "loc": {
                              "start": {
                                "line": 29,
                                "column": 7
                              },
                              "end": {
                                "line": 29,
                                "column": 11
                              }
                            }
                          },
                          "range": [
                            838,
                            845
                          ],
                          "loc": {
                            "start": {
                              "line": 29,
                              "column": 4
                            },
                            "end": {
                              "line": 29,
                              "column": 11
                            }
                          }
                        },
                        "right": {
                          "type": "BinaryExpression",
                          "operator": "+",
                          "left": {
                            "type": "MemberExpression",
                            "computed": false,
                            "object": {
                              "type": "Identifier",
                              "name": "location",
                              "range": [
                                848,
                                856
                              ],
                              "loc": {
                                "start": {
                                  "line": 29,
                                  "column": 14
                                },
                                "end": {
                                  "line": 29,
                                  "column": 22
                                }
                              }
                            },
                            "property": {
                              "type": "Identifier",
                              "name": "href",
                              "range": [
                                857,
                                861
                              ],
                              "loc": {
                                "start": {
                                  "line": 29,
                                  "column": 23
                                },
                                "end": {
                                  "line": 29,
                                  "column": 27
                                }
                              }
                            },
                            "range": [
                              848,
                              861
                            ],
                            "loc": {
                              "start": {
                                "line": 29,
                                "column": 14
                              },
                              "end": {
                                "line": 29,
                                "column": 27
                              }
                            }
                          },
                          "right": {
                            "type": "CallExpression",
                            "callee": {
                              "type": "MemberExpression",
                              "computed": false,
                              "object": {
                                "type": "Identifier",
                                "name": "el",
                                "range": [
                                  864,
                                  866
                                ],
                                "loc": {
                                  "start": {
                                    "line": 29,
                                    "column": 30
                                  },
                                  "end": {
                                    "line": 29,
                                    "column": 32
                                  }
                                }
                              },
                              "property": {
                                "type": "Identifier",
                                "name": "getAttribute",
                                "range": [
                                  867,
                                  879
                                ],
                                "loc": {
                                  "start": {
                                    "line": 29,
                                    "column": 33
                                  },
                                  "end": {
                                    "line": 29,
                                    "column": 45
                                  }
                                }
                              },
                              "range": [
                                864,
                                879
                              ],
                              "loc": {
                                "start": {
                                  "line": 29,
                                  "column": 30
                                },
                                "end": {
                                  "line": 29,
                                  "column": 45
                                }
                              }
                            },
                            "arguments": [
                              {
                                "type": "Literal",
                                "value": "href",
                                "raw": "'href'",
                                "range": [
                                  880,
                                  886
                                ],
                                "loc": {
                                  "start": {
                                    "line": 29,
                                    "column": 46
                                  },
                                  "end": {
                                    "line": 29,
                                    "column": 52
                                  }
                                }
                              }
                            ],
                            "range": [
                              864,
                              887
                            ],
                            "loc": {
                              "start": {
                                "line": 29,
                                "column": 30
                              },
                              "end": {
                                "line": 29,
                                "column": 53
                              }
                            }
                          },
                          "range": [
                            848,
                            887
                          ],
                          "loc": {
                            "start": {
                              "line": 29,
                              "column": 14
                            },
                            "end": {
                              "line": 29,
                              "column": 53
                            }
                          }
                        },
                        "range": [
                          838,
                          887
                        ],
                        "loc": {
                          "start": {
                            "line": 29,
                            "column": 4
                          },
                          "end": {
                            "line": 29,
                            "column": 53
                          }
                        }
                      },
                      "range": [
                        838,
                        888
                      ],
                      "loc": {
                        "start": {
                          "line": 29,
                          "column": 4
                        },
                        "end": {
                          "line": 29,
                          "column": 54
                        }
                      },
                      "trailingComments": [
                        {
                          "type": "Line",
                          "value": " because el.href is absolute path",
                          "range": [
                            889,
                            924
                          ],
                          "loc": {
                            "start": {
                              "line": 29,
                              "column": 55
                            },
                            "end": {
                              "line": 29,
                              "column": 90
                            }
                          }
                        }
                      ]
                    }
                  ],
                  "range": [
                    811,
                    928
                  ],
                  "loc": {
                    "start": {
                      "line": 27,
                      "column": 39
                    },
                    "end": {
                      "line": 30,
                      "column": 3
                    }
                  }
                },
                "range": [
                  774,
                  928
                ],
                "loc": {
                  "start": {
                    "line": 27,
                    "column": 2
                  },
                  "end": {
                    "line": 30,
                    "column": 3
                  }
                }
              }
            ],
            "range": [
              716,
              930
            ],
            "loc": {
              "start": {
                "line": 25,
                "column": 11
              },
              "end": {
                "line": 31,
                "column": 1
              }
            }
          },
          "generator": false,
          "expression": false,
          "range": [
            706,
            930
          ],
          "loc": {
            "start": {
              "line": 25,
              "column": 1
            },
            "end": {
              "line": 31,
              "column": 1
            }
          }
        },
        "arguments": [],
        "range": [
          705,
          933
        ],
        "loc": {
          "start": {
            "line": 25,
            "column": 0
          },
          "end": {
            "line": 31,
            "column": 4
          }
        }
      },
      "range": [
        705,
        934
      ],
      "loc": {
        "start": {
          "line": 25,
          "column": 0
        },
        "end": {
          "line": 31,
          "column": 5
        }
      }
    }
  ],
  "sourceType": "module",
  "range": [
    103,
    934
  ],
  "loc": {
    "start": {
      "line": 3,
      "column": 0
    },
    "end": {
      "line": 31,
      "column": 5
    }
  },
  "comments": [
    {
      "type": "Line",
      "value": " inner link(#foo) can not correctly scroll, because page has fixed header,",
      "range": [
        0,
        76
      ],
      "loc": {
        "start": {
          "line": 1,
          "column": 0
        },
        "end": {
          "line": 1,
          "column": 76
        }
      }
    },
    {
      "type": "Line",
      "value": " so, I manually scroll.",
      "range": [
        77,
        102
      ],
      "loc": {
        "start": {
          "line": 2,
          "column": 0
        },
        "end": {
          "line": 2,
          "column": 25
        }
      }
    },
    {
      "type": "Line",
      "value": " ``[ ] . ' \" @`` are not valid in DOM id. so must escape these.",
      "range": [
        369,
        434
      ],
      "loc": {
        "start": {
          "line": 12,
          "column": 4
        },
        "end": {
          "line": 12,
          "column": 69
        }
      }
    },
    {
      "type": "Line",
      "value": " because el.href is absolute path",
      "range": [
        889,
        924
      ],
      "loc": {
        "start": {
          "line": 29,
          "column": 55
        },
        "end": {
          "line": 29,
          "column": 90
        }
      }
    }
  ]
}